zettings/__init__.py
zettings/utils.py
zettings/zettings.py
zettings-1.0.0.dist-info/licenses/LICENSE
zettings-1.0.0.dist-info/METADATA
zettings-1.0.0.dist-info/WHEEL
zettings-1.0.0.dist-info/top_level.txt
zettings-1.0.0.dist-info/RECORD
