Metadata-Version: 2.4
Name: zettings
Version: 1.0.0
Summary: A lightweight, TOML-backed configuration/settings utility that that exposes project settings as standard Python dictionaries.
Author-email: Nick Stuer <nickstuer@duck.com>
Project-URL: Homepage, https://github.com/nickstuer/zettings
Project-URL: Issues, https://github.com/nickstuer/zettings/issues
Classifier: Development Status :: 5 - Production/Stable
Classifier: Programming Language :: Python :: 3
Classifier: License :: OSI Approved :: MIT License
Classifier: Operating System :: OS Independent
Requires-Python: >=3.9
License-File: LICENSE
Requires-Dist: toml>=0.10.2
Dynamic: license-file
